openpype/__init__.cp310-win_amd64.pyd
openpype/__init__.py
openpype/main.cp310-win_amd64.pyd
openpype/main.py
openpype/prod.cp310-win_amd64.pyd
openpype/prod.py
openpype-0.0.5.dist-info/METADATA
openpype-0.0.5.dist-info/WHEEL
openpype-0.0.5.dist-info/top_level.txt
openpype-0.0.5.dist-info/RECORD
