Metadata-Version: 2.1
Name: openpype
Version: 0.0.5
Summary: VFX Pipeline Tools
Author: initialfx
Author-email: initialfx@gmail.com
License: MIT
Requires-Python: >=3.10
Requires-Dist: gazu
Requires-Dist: pyreadline3
